statseis/__init__.py
statseis/cartopy_maps.py
statseis/foreshocks.py
statseis/geopandas_maps.py
statseis/mc.py
statseis/mc_lilliefors.py
statseis/utils.py
statseis-0.0.6.dist-info/METADATA
statseis-0.0.6.dist-info/WHEEL
statseis-0.0.6.dist-info/licenses/LICENCE
statseis-0.0.6.dist-info/RECORD
