Metadata-Version: 2.4
Name: statseis
Version: 0.0.6
Summary: Package to statistically analyse seismicity
Project-URL: Homepage, https://github.com/RussellAzadKhan/seispy
Author-email: RussellAzadKhan <russellazadkhan@gmail.com>
License-File: LICENCE
Classifier: License :: OSI Approved :: GNU General Public License v3 (GPLv3)
Classifier: Operating System :: OS Independent
Classifier: Programming Language :: Python :: 3
Requires-Python: >=3.8
Requires-Dist: cartopy
Requires-Dist: geopandas
Requires-Dist: ipython
Requires-Dist: matplotlib
Requires-Dist: numpy
Requires-Dist: pandas
Requires-Dist: plotly
Requires-Dist: pyproj
Requires-Dist: scipy
Requires-Dist: seaborn
Requires-Dist: shapely
Requires-Dist: statsmodels
Requires-Dist: tqdm
